briton_core.cpython-310-x86_64-linux-gnu.so
briton_lib-0.0.2.dist-info/METADATA
briton_lib-0.0.2.dist-info/WHEEL
briton_lib-0.0.2.dist-info/RECORD
